logiclayer/__init__.py
logiclayer/auth.py
logiclayer/common.py
logiclayer/decorators.py
logiclayer/logiclayer.py
logiclayer/module.py
logiclayer-0.4.4.dist-info/LICENSE
logiclayer-0.4.4.dist-info/METADATA
logiclayer-0.4.4.dist-info/WHEEL
logiclayer-0.4.4.dist-info/RECORD
