Metadata-Version: 2.3
Name: logiclayer
Version: 0.4.4
Summary: A framework to quickly compose and use multiple functionalities as endpoints.
License: MIT
Author: Francisco Abarzua
Author-email: francisco@datawheel.us
Requires-Python: >=3.9,<4.0
Classifier: License :: OSI Approved :: MIT License
Classifier: Programming Language :: Python :: 3
Classifier: Programming Language :: Python :: 3.9
Classifier: Programming Language :: Python :: 3.10
Classifier: Programming Language :: Python :: 3.11
Classifier: Programming Language :: Python :: 3.12
Classifier: Programming Language :: Python :: 3.13
Requires-Dist: asyncio (>=3.4.0,<4.0.0)
Requires-Dist: fastapi-slim (>=0.111,<1.0)
Requires-Dist: pydantic (>=2.5.0,<3.0.0)
Project-URL: Repository, https://github.com/Datawheel/logiclayer
